<?xml version="1.0" encoding="UTF-8"?>
<beans:beans xmlns="http://www.springframework.org/schema/mvc"
	xmlns:xsi="http://www.w3.org/2001/XMLSchema-instance" xmlns:beans="http://www.springframework.org/schema/beans"
	xmlns:context="http://www.springframework.org/schema/context"
	xmlns:util="http://www.springframework.org/schema/util"
	xsi:schemaLocation="http://www.springframework.org/schema/mvc http://www.springframework.org/schema/mvc/spring-mvc-3.2.xsd
        http://www.springframework.org/schema/beans http://www.springframework.org/schema/beans/spring-beans-3.2.xsd
        http://www.springframework.org/schema/context http://www.springframework.org/schema/context/spring-context-3.2.xsd
        http://www.springframework.org/schema/util http://www.springframework.org/schema/util/spring-util-3.2.xsd">

	<annotation-driven validator="validator">
		<argument-resolvers>
			<beans:bean class="com.meizu.ocean.common.binder.RenamingProcessor">
				<beans:constructor-arg name="annotationNotRequired"
					value="true" />
			</beans:bean>
		</argument-resolvers>
		<message-converters>
			<beans:ref bean="fastJsonHttpMessageConverter"/>
		</message-converters>
	</annotation-driven>

	<beans:bean id="validator"
		class="org.springframework.validation.beanvalidation.LocalValidatorFactoryBean">
		<beans:property name="validationMessageSource" ref="messageSource" />
	</beans:bean>
	
	<beans:bean id="fastJsonHttpMessageConverter"
		class="com.meizu.ocean.common.utils.FastJsonHttpMessageConverterX ">
		<beans:property name="supportedMediaTypes">
			<beans:list>
				<beans:value>application/json</beans:value>
                <beans:value>text/html;charset=UTF-8</beans:value>
            </beans:list>
        </beans:property> 
		<beans:property name="serializerFeatures">
			<beans:array>
				<beans:value>WriteMapNullValue</beans:value>
				<beans:value>QuoteFieldNames</beans:value>
			</beans:array>
		</beans:property>
	</beans:bean>
	
	<util:list id="messageConverters">
		<beans:ref bean="fastJsonHttpMessageConverter"/>
	</util:list>
	
	<beans:bean id="handlerExceptionResolver" class="com.meizu.ocean.common.exception.OceanHandlerExceptionResolverX">
		<beans:property name="messageConverters" ref="messageConverters"/>
	</beans:bean>
	
	<resources mapping="/favicon.ico" location="/favicon.ico" />
	<resources mapping="/resources/**" location="/resources/" />
	<resources mapping="/upload/**" location="/upload/" />
	
	<beans:bean id="viewResolver" class="org.springframework.web.servlet.view.freemarker.FreeMarkerViewResolver">
	    <beans:property name="viewClass" value="org.springframework.web.servlet.view.freemarker.FreeMarkerView"/>
	    <beans:property name="suffix" value=".htm" />
	    <beans:property name="contentType" value="text/html;charset=utf-8"/>
	    <beans:property name="exposeRequestAttributes" value="true" />  
        <beans:property name="exposeSessionAttributes" value="true" />  
        <beans:property name="exposeSpringMacroHelpers" value="true" />  
	</beans:bean>
	
	<beans:bean id="localeResolver" class="org.springframework.web.servlet.i18n.AcceptHeaderLocaleResolver" /> 

	<beans:bean id="multipartResolver"
		class="org.springframework.web.multipart.commons.CommonsMultipartResolver">
		<beans:property name="defaultEncoding" value="UTF-8" />
		<beans:property name="maxUploadSize" value="524288000" />
		<beans:property name="maxInMemorySize" value="10240" />
	</beans:bean>
	
	<beans:import resource="classpath*:config/manage-controllers.xml" />
</beans:beans>
